mlpredictor/__init__.py
mlpredictor/model.py
mlpredictorchris-0.1.0.dist-info/licenses/LICENSE
mlpredictorchris-0.1.0.dist-info/METADATA
mlpredictorchris-0.1.0.dist-info/WHEEL
mlpredictorchris-0.1.0.dist-info/top_level.txt
mlpredictorchris-0.1.0.dist-info/RECORD
