Metadata-Version: 2.4
Name: mlpredictorchris
Version: 0.1.0
Summary: A simple machine learning package using scikit-learn
Author-email: Chris America <chris.america@hotmail.com>
License: MIT
Project-URL: Homepage, https://github.com/chrisamerica1995/mlpredictor
Requires-Python: >=3.6
License-File: LICENSE
Requires-Dist: scikit-learn>=1.0
Dynamic: license-file
